dottorrentGUI/__init__.py
dottorrentGUI/gui.py
dottorrentGUI/ui_about.py
dottorrentGUI/ui_mainwindow.py
dottorrentGUI/version.py
dottorrent_gui-1.3.11.dist-info/DESCRIPTION.rst
dottorrent_gui-1.3.11.dist-info/METADATA
dottorrent_gui-1.3.11.dist-info/RECORD
dottorrent_gui-1.3.11.dist-info/WHEEL
dottorrent_gui-1.3.11.dist-info/entry_points.txt
dottorrent_gui-1.3.11.dist-info/metadata.json
dottorrent_gui-1.3.11.dist-info/top_level.txt
