Metadata-Version: 2.0
Name: dottorrent-gui
Version: 1.3.11
Summary: An advanced GUI torrent file creator with batch functionality, powered by PyQt and dottorrent
Home-page: https://github.com/kz26/dottorrent-gui
Author: Kevin Zhang
Author-email: kevin@kevinzhang.me
License: UNKNOWN
Keywords: bittorrent torrent
Platform: UNKNOWN
Classifier: Development Status :: 5 - Production/Stable
Classifier: Intended Audience :: End Users/Desktop
Classifier: License :: OSI Approved :: GNU General Public License v3 (GPLv3)
Classifier: Programming Language :: Python :: 3.3
Classifier: Programming Language :: Python :: 3.4
Classifier: Programming Language :: Python :: 3.5
Classifier: Programming Language :: Python :: 3.6
Requires-Dist: PyQt5 (>=5.7)
Requires-Dist: dottorrent (>=1.9.2)
Requires-Dist: humanfriendly
